{
    "id": 995218710,
    "number": 4827,
    "threads": 7,
    "type": "email",
    "folderId": 2307530,
    "status": "closed",
    "state": "published",
    "subject": "Re: FW: embed code",
    "preview": "Hi Lizzy,Sure, the space between the live stream screen and major sponsor has been decreased. Let me know if this is ok for you?",
    "mailboxId": 158894,
    "createdBy": {
        "id": 204600834,
        "type": "customer",
        "first": "Lizzy",
        "last": "Morton",
        "photoUrl": "https://d33v4339jhl8k0.cloudfront.net/customer-avatar/05.png",
        "email": "emorton@msra.org.au"
    },
    "createdAt": "2019-11-01T02:27:41Z",
    "closedBy": 309820,
    "closedByUser": {
        "id": 309820,
        "type": "user",
        "first": "Joel",
        "last": "Maligalig",
        "photoUrl": "https://d33v4339jhl8k0.cloudfront.net/users/309820.341294.jpg",
        "email": "joel@wolfiq.com.au"
    },
    "closedAt": "2019-11-01T04:02:30Z",
    "userUpdatedAt": "2019-11-01T04:02:30Z",
    "customerWaitingSince": {
        "time": "2019-11-01T04:02:30Z",
        "friendly": "Nov 1, '19"
    },
    "source": {
        "type": "email",
        "via": "customer"
    },
    "tags": [],
    "cc": [
        "heath@wpperk.com"
    ],
    "bcc": [],
    "primaryCustomer": {
        "id": 204600834,
        "type": "customer",
        "first": "Lizzy",
        "last": "Morton",
        "photoUrl": "https://d33v4339jhl8k0.cloudfront.net/customer-avatar/05.png",
        "email": "emorton@msra.org.au"
    },
    "customFields": [],
    "_embedded": {
        "threads": []
    },
    "_links": {
        "self": {
            "href": "https://api.helpscout.net/v2/conversations/995218710"
        },
        "mailbox": {
            "href": "https://api.helpscout.net/v2/mailboxes/158894"
        },
        "primaryCustomer": {
            "href": "https://api.helpscout.net/v2/customers/204600834"
        },
        "createdByCustomer": {
            "href": "https://api.helpscout.net/v2/customers/204600834"
        },
        "closedBy": {
            "href": "https://api.helpscout.net/v2/users/309820"
        },
        "threads": {
            "href": "https://api.helpscout.net/v2/conversations/995218710/threads"
        },
        "web": {
            "href": "https://secure.helpscout.net/conversation/995218710/4827"
        }
    },
    "full_threads": [
        {
            "id": 2804039598,
            "type": "message",
            "status": "closed",
            "state": "published",
            "action": {
                "type": "original-author",
                "associatedEntities": {
                    "user": 309820
                }
            },
            "body": "Hi Lizzy,<br /><br />Sure, the space between the live stream screen and major sponsor has been decreased. Let me know if this is ok for you?",
            "source": {
                "type": "web",
                "via": "user"
            },
            "customer": {
                "id": 204600834,
                "first": "Lizzy",
                "last": "Morton",
                "photoUrl": "https://d33v4339jhl8k0.cloudfront.net/customer-avatar/05.png",
                "email": "emorton@msra.org.au"
            },
            "createdBy": {
                "id": 309820,
                "type": "user",
                "first": "Joel",
                "last": "Maligalig",
                "photoUrl": "https://d33v4339jhl8k0.cloudfront.net/users/309820.341294.jpg",
                "email": "joel@wolfiq.com.au"
            },
            "assignedTo": {
                "id": 1,
                "first": "Help",
                "last": "Scout",
                "email": "none@nowhere.com"
            },
            "savedReplyId": 0,
            "to": [],
            "cc": [
                "heath@wpperk.com"
            ],
            "bcc": [],
            "createdAt": "2019-11-01T04:02:30Z",
            "openedAt": "2019-11-01T04:14:40Z",
            "_embedded": {
                "attachments": []
            },
            "_links": {
                "assignedTo": {
                    "href": "https://api.helpscout.net/v2/users/1"
                },
                "createdByUser": {
                    "href": "https://api.helpscout.net/v2/users/309820"
                },
                "customer": {
                    "href": "https://api.helpscout.net/v2/customers/204600834"
                }
            }
        },
        {
            "id": 2804027228,
            "type": "customer",
            "status": "active",
            "state": "published",
            "action": {
                "type": "default",
                "associatedEntities": {}
            },
            "body": "Sorry to be a pain - could you close the gap beneath the live stream embedded screen and the major sponsor section? So there is much less white space between them?<br><br>Thanks<br><br>Lizzy",
            "source": {
                "type": "email",
                "via": "customer"
            },
            "customer": {
                "id": 204600834,
                "first": "Lizzy",
                "last": "Morton",
                "photoUrl": "https://d33v4339jhl8k0.cloudfront.net/customer-avatar/05.png",
                "email": "emorton@msra.org.au"
            },
            "createdBy": {
                "id": 204600834,
                "type": "customer",
                "first": "Lizzy",
                "last": "Morton",
                "photoUrl": "https://d33v4339jhl8k0.cloudfront.net/customer-avatar/05.png",
                "email": "emorton@msra.org.au"
            },
            "assignedTo": {
                "id": 1,
                "first": "Help",
                "last": "Scout",
                "email": "none@nowhere.com"
            },
            "savedReplyId": 0,
            "to": [],
            "cc": [
                "heath@wpperk.com"
            ],
            "bcc": [],
            "createdAt": "2019-11-01T03:50:14Z",
            "_embedded": {
                "attachments": []
            },
            "_links": {
                "assignedTo": {
                    "href": "https://api.helpscout.net/v2/users/1"
                },
                "createdByCustomer": {
                    "href": "https://api.helpscout.net/v2/customers/204600834"
                },
                "customer": {
                    "href": "https://api.helpscout.net/v2/customers/204600834"
                }
            }
        },
        {
            "id": 2804020956,
            "type": "message",
            "status": "closed",
            "state": "published",
            "action": {
                "type": "original-author",
                "associatedEntities": {
                    "user": 309820
                }
            },
            "body": "Hi Lizzy,<br /><br />Sure, all good now on this one.\u00a0<br /><a href=\"https://msra.org.au/events/liveupdate2019/livestream/\">https://msra.org.au/events/liveupdate2019/livestream/</a><br /><br />Let me know if this works for you?",
            "source": {
                "type": "web",
                "via": "user"
            },
            "customer": {
                "id": 204600834,
                "first": "Lizzy",
                "last": "Morton",
                "photoUrl": "https://d33v4339jhl8k0.cloudfront.net/customer-avatar/05.png",
                "email": "emorton@msra.org.au"
            },
            "createdBy": {
                "id": 309820,
                "type": "user",
                "first": "Joel",
                "last": "Maligalig",
                "photoUrl": "https://d33v4339jhl8k0.cloudfront.net/users/309820.341294.jpg",
                "email": "joel@wolfiq.com.au"
            },
            "assignedTo": {
                "id": 1,
                "first": "Help",
                "last": "Scout",
                "email": "none@nowhere.com"
            },
            "savedReplyId": 0,
            "to": [],
            "cc": [
                "heath@wpperk.com"
            ],
            "bcc": [],
            "createdAt": "2019-11-01T03:44:52Z",
            "openedAt": "2019-11-01T03:48:27Z",
            "_embedded": {
                "attachments": []
            },
            "_links": {
                "assignedTo": {
                    "href": "https://api.helpscout.net/v2/users/1"
                },
                "createdByUser": {
                    "href": "https://api.helpscout.net/v2/users/309820"
                },
                "customer": {
                    "href": "https://api.helpscout.net/v2/customers/204600834"
                }
            }
        },
        {
            "id": 2804000172,
            "type": "customer",
            "status": "active",
            "state": "published",
            "action": {
                "type": "default",
                "associatedEntities": {}
            },
            "body": "Just sending to the other email too to ensure you get this as time is against us a bit today J",
            "source": {
                "type": "email",
                "via": "customer"
            },
            "customer": {
                "id": 204600834,
                "first": "Lizzy",
                "last": "Morton",
                "photoUrl": "https://d33v4339jhl8k0.cloudfront.net/customer-avatar/05.png",
                "email": "emorton@msra.org.au"
            },
            "createdBy": {
                "id": 204600834,
                "type": "customer",
                "first": "Lizzy",
                "last": "Morton",
                "photoUrl": "https://d33v4339jhl8k0.cloudfront.net/customer-avatar/05.png",
                "email": "emorton@msra.org.au"
            },
            "assignedTo": {
                "id": 1,
                "first": "Help",
                "last": "Scout",
                "email": "none@nowhere.com"
            },
            "savedReplyId": 0,
            "to": [
                "support@wpperk.com",
                "heath@wpperk.com"
            ],
            "cc": [],
            "bcc": [],
            "createdAt": "2019-11-01T03:26:13Z",
            "_embedded": {
                "attachments": []
            },
            "_links": {
                "assignedTo": {
                    "href": "https://api.helpscout.net/v2/users/1"
                },
                "createdByCustomer": {
                    "href": "https://api.helpscout.net/v2/customers/204600834"
                },
                "customer": {
                    "href": "https://api.helpscout.net/v2/customers/204600834"
                }
            }
        },
        {
            "id": 2803983772,
            "type": "customer",
            "status": "active",
            "state": "published",
            "action": {
                "type": "default",
                "associatedEntities": {}
            },
            "body": "Great - thanks Heath!<br><br>Now that's on there, please could you remove the whole blue countdown section directly below it?<br><br>So it will now just have the live stream embedded window and then directly below it goes to 'Major sponsor Roche' etc etc.<br><br>Could you also make the header banner a lot thinner on this page, so that the embedded window is at least part-visible without scrolling?<br><br>Thanks<br><br>Lizzy",
            "source": {
                "type": "email",
                "via": "customer"
            },
            "customer": {
                "id": 204600834,
                "first": "Lizzy",
                "last": "Morton",
                "photoUrl": "https://d33v4339jhl8k0.cloudfront.net/customer-avatar/05.png",
                "email": "emorton@msra.org.au"
            },
            "createdBy": {
                "id": 204600834,
                "type": "customer",
                "first": "Lizzy",
                "last": "Morton",
                "photoUrl": "https://d33v4339jhl8k0.cloudfront.net/customer-avatar/05.png",
                "email": "emorton@msra.org.au"
            },
            "assignedTo": {
                "id": 1,
                "first": "Help",
                "last": "Scout",
                "email": "none@nowhere.com"
            },
            "savedReplyId": 0,
            "to": [],
            "cc": [],
            "bcc": [],
            "createdAt": "2019-11-01T03:11:35Z",
            "_embedded": {
                "attachments": []
            },
            "_links": {
                "assignedTo": {
                    "href": "https://api.helpscout.net/v2/users/1"
                },
                "createdByCustomer": {
                    "href": "https://api.helpscout.net/v2/customers/204600834"
                },
                "customer": {
                    "href": "https://api.helpscout.net/v2/customers/204600834"
                }
            }
        },
        {
            "id": 2803959786,
            "type": "message",
            "status": "closed",
            "state": "published",
            "action": {
                "type": "original-author",
                "associatedEntities": {
                    "user": 309027
                }
            },
            "body": "Hi Lizzy,\u00a0<br /><br />Sure, here you go: <a href=\"https://msra.org.au/events/liveupdate2019/livestream/\">https://msra.org.au/events/liveupdate2019/livestream/</a>",
            "source": {
                "type": "web",
                "via": "user"
            },
            "customer": {
                "id": 204600834,
                "first": "Lizzy",
                "last": "Morton",
                "photoUrl": "https://d33v4339jhl8k0.cloudfront.net/customer-avatar/05.png",
                "email": "emorton@msra.org.au"
            },
            "createdBy": {
                "id": 309027,
                "type": "user",
                "first": "Heath",
                "last": "Maguire",
                "photoUrl": "https://d33v4339jhl8k0.cloudfront.net/users/309027.237921.jpg",
                "email": "heath.maguire@wolfiq.com.au"
            },
            "assignedTo": {
                "id": 1,
                "first": "Help",
                "last": "Scout",
                "email": "none@nowhere.com"
            },
            "savedReplyId": 0,
            "to": [],
            "cc": [],
            "bcc": [],
            "createdAt": "2019-11-01T02:48:28Z",
            "openedAt": "2019-11-01T02:50:13Z",
            "_embedded": {
                "attachments": []
            },
            "_links": {
                "assignedTo": {
                    "href": "https://api.helpscout.net/v2/users/1"
                },
                "createdByUser": {
                    "href": "https://api.helpscout.net/v2/users/309027"
                },
                "customer": {
                    "href": "https://api.helpscout.net/v2/customers/204600834"
                }
            }
        },
        {
            "id": 2803938542,
            "type": "customer",
            "status": "active",
            "state": "published",
            "action": {
                "type": "default",
                "associatedEntities": {}
            },
            "body": "<div>\n<span style=\"font-size:11pt;font-family:Calibri, sans-serif;color:#1F497D;\">Let me know how you go</span> <span style=\"font-size:11pt;font-family:Wingdings;color:#1F497D;\">J</span><span style=\"font-size:11pt;font-family:Calibri, sans-serif;color:#1F497D;\"></span><br><span style=\"font-size:11pt;font-family:Calibri, sans-serif;color:#1F497D;\"></span><p></p><br><div style=\"border:none;border-top:solid #E1E1E1 1pt;padding:3pt 0cm 0cm 0cm;\">\n<p><b><span lang=\"en-us\" style=\"font-size:11pt;font-family:Calibri, sans-serif;\" xml:lang=\"en-us\">From:</span></b> <span lang=\"en-us\" style=\"font-size:11pt;font-family:Calibri, sans-serif;\" xml:lang=\"en-us\">Matt Yates [mailto:myates@scenechange.com.au]<br><b>Sent:</b> Friday, 1 November 2019 1:34 PM<br><b>To:</b> Lizzy Morton &lt;emorton@msra.org.au&gt;<br><b>Subject:</b> embed code</span></p>\n</div>\n<br>\n&lt;iframe src=\"//<a href=\"http://iframe.dacast.com/b/74528/c/512256\">iframe.dacast.com/b/74528/c/512256</a>\" width=\"1280\" height=\"720\" frameborder=\"0\" scrolling=\"no\" allow=\"autoplay\" allowfullscreen webkitallowfullscreen mozallowfullscreen oallowfullscreen msallowfullscreen&gt;&lt;/iframe&gt;<br><div>\n<br></div>\n<div>\n<br><div>\n<img border=\"0\" width=\"600\" height=\"120\" src=\"https://d33v4339jhl8k0.cloudfront.net/inline/87172/6656bb3b91e7f0aa7c254bfe8f116df0a525feba/a7dc02b7d273b816a0d29f9f6582133ff03085af/Scene-Change_Email-Sig_FINAL_VIC3.png\" alt=\"https://d33v4339jhl8k0.cloudfront.net/inline/87172/6656bb3b91e7f0aa7c254bfe8f116df0a525feba/a7dc02b7d273b816a0d29f9f6582133ff03085af/Scene-Change_Email-Sig_FINAL_VIC3.png\" /><br></div>\n<br></div>\n</div>",
            "source": {
                "type": "email",
                "via": "customer"
            },
            "customer": {
                "id": 204600834,
                "first": "Lizzy",
                "last": "Morton",
                "photoUrl": "https://d33v4339jhl8k0.cloudfront.net/customer-avatar/05.png",
                "email": "emorton@msra.org.au"
            },
            "createdBy": {
                "id": 204600834,
                "type": "customer",
                "first": "Lizzy",
                "last": "Morton",
                "photoUrl": "https://d33v4339jhl8k0.cloudfront.net/customer-avatar/05.png",
                "email": "emorton@msra.org.au"
            },
            "assignedTo": {
                "id": 1,
                "first": "Help",
                "last": "Scout",
                "email": "none@nowhere.com"
            },
            "savedReplyId": 0,
            "to": [
                "support@wpperk.com",
                "heath@wpperk.com"
            ],
            "cc": [],
            "bcc": [],
            "createdAt": "2019-11-01T02:27:41Z",
            "_embedded": {
                "attachments": []
            },
            "_links": {
                "assignedTo": {
                    "href": "https://api.helpscout.net/v2/users/1"
                },
                "createdByCustomer": {
                    "href": "https://api.helpscout.net/v2/customers/204600834"
                },
                "customer": {
                    "href": "https://api.helpscout.net/v2/customers/204600834"
                }
            }
        }
    ]
}