{
    "id": 1414459698,
    "number": 11677,
    "threads": 5,
    "type": "email",
    "folderId": 2307530,
    "status": "closed",
    "state": "published",
    "subject": "Re: Axiom website - Our story page - Team photos",
    "preview": "Hi Sarah-Jane,No worries I've checked the existing images and found out that they are round images before it was uploaded on the page. Yes, we can help you edit the images. If you want, you can provid",
    "mailboxId": 158894,
    "assignee": {
        "id": 481974,
        "type": "user",
        "first": "Rica",
        "last": "Rosario Valencia",
        "email": "rica@wolfiq.com.au"
    },
    "createdBy": {
        "id": 234333118,
        "type": "customer",
        "first": "Sarah-Jane",
        "last": "Lamont",
        "photoUrl": "https://d33v4339jhl8k0.cloudfront.net/customer-avatar/05.png",
        "email": "sarah-jane.lamont@axiomworkplaces.com.au"
    },
    "createdAt": "2021-02-03T00:39:12Z",
    "closedBy": 481974,
    "closedByUser": {
        "id": 481974,
        "type": "user",
        "first": "Rica",
        "last": "Rosario Valencia",
        "photoUrl": "https://d33v4339jhl8k0.cloudfront.net/users/481974.341283.jpg",
        "email": "rica@wolfiq.com.au"
    },
    "closedAt": "2021-02-04T22:34:02Z",
    "userUpdatedAt": "2021-02-04T22:34:02Z",
    "customerWaitingSince": {
        "time": "2021-02-04T22:34:02Z",
        "friendly": "Feb 5, '21"
    },
    "source": {
        "type": "email",
        "via": "customer"
    },
    "tags": [],
    "cc": [],
    "bcc": [],
    "primaryCustomer": {
        "id": 234333118,
        "type": "customer",
        "first": "Sarah-Jane",
        "last": "Lamont",
        "photoUrl": "https://d33v4339jhl8k0.cloudfront.net/customer-avatar/05.png",
        "email": "sarah-jane.lamont@axiomworkplaces.com.au"
    },
    "customFields": [],
    "_embedded": {
        "threads": []
    },
    "_links": {
        "self": {
            "href": "https://api.helpscout.net/v2/conversations/1414459698"
        },
        "mailbox": {
            "href": "https://api.helpscout.net/v2/mailboxes/158894"
        },
        "primaryCustomer": {
            "href": "https://api.helpscout.net/v2/customers/234333118"
        },
        "createdByCustomer": {
            "href": "https://api.helpscout.net/v2/customers/234333118"
        },
        "closedBy": {
            "href": "https://api.helpscout.net/v2/users/481974"
        },
        "threads": {
            "href": "https://api.helpscout.net/v2/conversations/1414459698/threads"
        },
        "assignee": {
            "href": "https://api.helpscout.net/v2/users/481974"
        },
        "web": {
            "href": "https://secure.helpscout.net/conversation/1414459698/11677"
        }
    },
    "full_threads": [
        {
            "id": 4097485870,
            "type": "lineitem",
            "status": "closed",
            "action": {
                "type": "default",
                "text": "Rica Rosario Valencia marked as Closed",
                "associatedEntities": {}
            },
            "source": {
                "type": "web",
                "via": "user"
            },
            "createdBy": {
                "id": 481974,
                "type": "user",
                "first": "Rica",
                "last": "Rosario Valencia",
                "email": "rica@wolfiq.com.au"
            },
            "to": [],
            "cc": [],
            "bcc": [],
            "createdAt": "2021-02-04T22:34:02Z",
            "_embedded": {
                "attachments": []
            },
            "_links": {
                "createdByUser": {
                    "href": "https://api.helpscout.net/v2/users/481974"
                }
            }
        },
        {
            "id": 4090615921,
            "type": "message",
            "status": "pending",
            "state": "published",
            "action": {
                "type": "original-author",
                "associatedEntities": {
                    "user": 481974
                }
            },
            "body": "Hi Sarah-Jane,<br /><br />No worries I've checked the existing images and found out that they are round images before it was uploaded on the page. Yes, we can help you edit the images. If you want, you can provide us the copy and the images so we'll be the one to update the page for you.<br />",
            "source": {
                "type": "web",
                "via": "user"
            },
            "customer": {
                "id": 234333118,
                "first": "Sarah-Jane",
                "last": "Lamont",
                "photoUrl": "https://d33v4339jhl8k0.cloudfront.net/customer-avatar/05.png",
                "email": "sarah-jane.lamont@axiomworkplaces.com.au"
            },
            "createdBy": {
                "id": 481974,
                "type": "user",
                "first": "Rica",
                "last": "Rosario Valencia",
                "photoUrl": "https://d33v4339jhl8k0.cloudfront.net/users/481974.341283.jpg",
                "email": "rica@wolfiq.com.au"
            },
            "assignedTo": {
                "id": 481974,
                "type": "user",
                "first": "Rica",
                "last": "Rosario Valencia",
                "photoUrl": "https://d33v4339jhl8k0.cloudfront.net/users/481974.341283.jpg",
                "email": "rica@wolfiq.com.au"
            },
            "savedReplyId": 0,
            "to": [],
            "cc": [],
            "bcc": [],
            "createdAt": "2021-02-03T03:05:17Z",
            "_embedded": {
                "attachments": []
            },
            "_links": {
                "assignedTo": {
                    "href": "https://api.helpscout.net/v2/users/481974"
                },
                "createdByUser": {
                    "href": "https://api.helpscout.net/v2/users/481974"
                },
                "customer": {
                    "href": "https://api.helpscout.net/v2/customers/234333118"
                }
            }
        },
        {
            "id": 4090531031,
            "type": "customer",
            "status": "active",
            "state": "published",
            "action": {
                "type": "default",
                "associatedEntities": {}
            },
            "body": "Sorry, one other thing. I had some short notice to update another image on the Why Axiom? page: https://axiomworkplaces.com.au/our-impact/<br><br>There are 4 photos associated with the 4 reasons of \"Why Axiom?\" I had to replace the Multigenerational Workforces one, however it came through as square as opposed to round like the others. Are you able to make it round or is this something I need to do in photoshop before uploading?<br><br><img border=\"0\" width=\"578\" height=\"346\" style=\"width:6.0208in;height:3.6041in;\" name=\"ex-Picture_x0020_13\" src=\"https://d33v4339jhl8k0.cloudfront.net/inline/87172/6083da821c8f76bcc8b53553110884854cf399b7/f51ace317e0e11a31b99e98d738d14600957bb8d/image005.jpg\" alt=\"image005.jpg@01D6FA2C.E54CD0D0\"/><img border=\"0\" width=\"624\" height=\"340\" style=\"width:6.5in;height:3.5416in;\" name=\"ex-Picture_x0020_14\" src=\"https://d33v4339jhl8k0.cloudfront.net/inline/87172/f254f8aaddc62ce5a42975c581cbbf002cd3266c/c7708736372c84dc27cbc285bf378a8a9f277a45/image006.jpg\" alt=\"image006.jpg@01D6FA2C.E54CD0D0\"/><br><br>Kindest Regards,<br><br>Sarah-Jane Lamont<br><br>Client Relations Executive Assistant<br><br><strong>T</strong> 1300 11 22 32<br><br><strong>M</strong> 0421 478 501<br><br><strong>E</strong> sarah-jane.lamont@axiomworkplaces.com.au<br><br><strong>LI</strong> <a href=\"https://www.linkedin.com/in/sarah-jane-lamont-93542627/\">linkedin.com/in/sarah-jane-lamont-93542627/</a><br><br><strong>W</strong> http://axiomworkplaces.com.au/<br><br><a href=\"https://www.linkedin.com/company/axiom-workplaces\"><img border=\"0\" width=\"30\" height=\"30\" style=\"width:0.3125in;height:0.3125in;\" alt=\"social-_0007_Vector-Smart-Object\" name=\"ex-Picture_x0020_8\" src=\"https://d33v4339jhl8k0.cloudfront.net/inline/87172/abf4e62a14f89bb1bda58439b289b5634d48e61c/dd6bf8c51b8476941db76dc5de2f4720d835825e/image001.png\"/></a> <a href=\"https://www.instagram.com/axiom_workplaces/\"><img border=\"0\" width=\"30\" height=\"30\" style=\"width:0.3125in;height:0.3125in;\" alt=\"social-_0006_Vector-Smart-Object\" name=\"ex-Picture_x0020_9\" src=\"https://d33v4339jhl8k0.cloudfront.net/inline/87172/0ce7ce899045fcff6b2148a811f4beb7e53af928/ea4417351269cbe4e1ba5dabe135e55b66824532/image002.png\"/></a> <a href=\"https://www.facebook.com/AxiomWorkplaces/\"><img border=\"0\" width=\"30\" height=\"30\" style=\"width:0.3125in;height:0.3125in;\" alt=\"social-_0005_Vector-Smart-Object\" name=\"ex-Picture_x0020_10\" src=\"https://d33v4339jhl8k0.cloudfront.net/inline/87172/aa9acfe2b1e34421b091d21b2ff6dbf1b62e6d6a/3bb5ea8e79292980a5d2d99c5e589900d39d9d81/image003.png\"/></a> <a href=\"https://www.pinterest.com/axiomworkplaces\"><img border=\"0\" width=\"30\" height=\"30\" style=\"width:0.3125in;height:0.3125in;\" alt=\"social-_0004_Vector-Smart-Object\" name=\"ex-Picture_x0020_11\" src=\"https://d33v4339jhl8k0.cloudfront.net/inline/87172/df9ba7d2519f18cac99222a35db44042b2a03a0f/b22b15965b844c33d29138a8e640c62f759c16f7/image004.png\"/></a><br><br><a href=\"https://axiomworkplaces.com.au/our-insight/what-does-the-future-of-work-look-like-for-employees-employers-and-workplaces/\"><img border=\"0\" width=\"623\" height=\"162\" style=\"width:6.4895in;height:1.6875in;\" name=\"ex-Picture_x0020_12\" src=\"https://d33v4339jhl8k0.cloudfront.net/inline/87172/da196b0e921b3a6257f9cc8208059d1fac19c7f4/b05b9a717909efe554ebb5ca258587dcebe83c60/image007.jpg\" alt=\"image007.jpg@01D6FA2C.E54CD0D0\"/></a><br><br>This e-mail may contain confidential and/or privileged information. If you are not the intended recipient (or have received this e-mail in error) please notify the sender immediately and destroy this e-mail. Any unauthorised copying, disclosure or distribution of the material in this e-mail is strictly forbidden. Axiom respects your privacy and is bound by the Australian Privacy Principles. If this email consists of direct marketing material and you would prefer to be removed from the mailing list, please reply to this email with the word \"Unsubscribe\" as the Subject.",
            "source": {
                "type": "email",
                "via": "customer"
            },
            "customer": {
                "id": 234333118,
                "first": "Sarah-Jane",
                "last": "Lamont",
                "photoUrl": "https://d33v4339jhl8k0.cloudfront.net/customer-avatar/05.png",
                "email": "sarah-jane.lamont@axiomworkplaces.com.au"
            },
            "createdBy": {
                "id": 234333118,
                "type": "customer",
                "first": "Sarah-Jane",
                "last": "Lamont",
                "photoUrl": "https://d33v4339jhl8k0.cloudfront.net/customer-avatar/05.png",
                "email": "sarah-jane.lamont@axiomworkplaces.com.au"
            },
            "assignedTo": {
                "id": 481974,
                "type": "user",
                "first": "Rica",
                "last": "Rosario Valencia",
                "photoUrl": "https://d33v4339jhl8k0.cloudfront.net/users/481974.341283.jpg",
                "email": "rica@wolfiq.com.au"
            },
            "savedReplyId": 0,
            "to": [],
            "cc": [],
            "bcc": [],
            "createdAt": "2021-02-03T02:04:03Z",
            "_embedded": {
                "attachments": [
                    {
                        "id": 332782155,
                        "filename": "image008.jpg",
                        "mimeType": "image/jpeg",
                        "width": 150,
                        "height": 68,
                        "size": 460,
                        "state": "valid",
                        "_links": {
                            "self": {
                                "href": "https://api.helpscout.net/v2/conversations/1414459698/attachments/332782155"
                            },
                            "data": {
                                "href": "https://api.helpscout.net/v2/conversations/1414459698/attachments/332782155/data"
                            },
                            "web": {
                                "href": "https://secure.helpscout.net/file/api/332782155/f4c89745fb4d8800d39fa3edb2e87089e181f60b/image008.jpg"
                            }
                        }
                    },
                    {
                        "id": 332782156,
                        "filename": "image009.jpg",
                        "mimeType": "image/jpeg",
                        "width": 30,
                        "height": 30,
                        "size": 344,
                        "state": "valid",
                        "_links": {
                            "self": {
                                "href": "https://api.helpscout.net/v2/conversations/1414459698/attachments/332782156"
                            },
                            "data": {
                                "href": "https://api.helpscout.net/v2/conversations/1414459698/attachments/332782156/data"
                            },
                            "web": {
                                "href": "https://secure.helpscout.net/file/api/332782156/fd8988fd2c8c42a9b5ce3bc2862b8828105f4af9/image009.jpg"
                            }
                        }
                    },
                    {
                        "id": 332782157,
                        "filename": "image016.jpg",
                        "mimeType": "image/jpeg",
                        "width": 623,
                        "height": 162,
                        "size": 1560,
                        "state": "valid",
                        "_links": {
                            "self": {
                                "href": "https://api.helpscout.net/v2/conversations/1414459698/attachments/332782157"
                            },
                            "data": {
                                "href": "https://api.helpscout.net/v2/conversations/1414459698/attachments/332782157/data"
                            },
                            "web": {
                                "href": "https://secure.helpscout.net/file/api/332782157/7623fd7135eb6cb6235dfe251a325d82de47c8fe/image016.jpg"
                            }
                        }
                    }
                ]
            },
            "_links": {
                "assignedTo": {
                    "href": "https://api.helpscout.net/v2/users/481974"
                },
                "createdByCustomer": {
                    "href": "https://api.helpscout.net/v2/customers/234333118"
                },
                "customer": {
                    "href": "https://api.helpscout.net/v2/customers/234333118"
                }
            }
        },
        {
            "id": 4090520337,
            "type": "lineitem",
            "status": "closed",
            "action": {
                "type": "default",
                "text": "Rica Rosario Valencia marked as Closed",
                "associatedEntities": {}
            },
            "source": {
                "type": "web",
                "via": "user"
            },
            "createdBy": {
                "id": 481974,
                "type": "user",
                "first": "Rica",
                "last": "Rosario Valencia",
                "email": "rica@wolfiq.com.au"
            },
            "to": [],
            "cc": [],
            "bcc": [],
            "createdAt": "2021-02-03T01:56:58Z",
            "_embedded": {
                "attachments": []
            },
            "_links": {
                "createdByUser": {
                    "href": "https://api.helpscout.net/v2/users/481974"
                }
            }
        },
        {
            "id": 4090518902,
            "type": "customer",
            "status": "active",
            "state": "published",
            "action": {
                "type": "default",
                "associatedEntities": {}
            },
            "body": "Thanks Rica, that's great. I will have more to add next week so please let me know if there is anything I can do on my end to prevent any glitches.<br><br>Kindest Regards,<br><br>Sarah-Jane Lamont<br><br>Client Relations Executive Assistant<br><br><strong>T</strong> 1300 11 22 32<br><br><strong>M</strong> 0421 478 501<br><br><strong>E</strong> sarah-jane.lamont@axiomworkplaces.com.au<br><br><strong>LI</strong> <a href=\"https://www.linkedin.com/in/sarah-jane-lamont-93542627/\">linkedin.com/in/sarah-jane-lamont-93542627/</a><br><br><strong>W</strong> http://axiomworkplaces.com.au/<br><br><a href=\"https://www.linkedin.com/company/axiom-workplaces\"><img border=\"0\" width=\"30\" height=\"30\" style=\"width:0.3125in;height:0.3125in;\" alt=\"social-_0007_Vector-Smart-Object\" name=\"ex-Picture_x0020_8\" src=\"https://d33v4339jhl8k0.cloudfront.net/inline/87172/ef476154322d77b3a771422728c1f011afc3ea7a/dd6bf8c51b8476941db76dc5de2f4720d835825e/image001.png\"/></a> <a href=\"https://www.instagram.com/axiom_workplaces/\"><img border=\"0\" width=\"30\" height=\"30\" style=\"width:0.3125in;height:0.3125in;\" alt=\"social-_0006_Vector-Smart-Object\" name=\"ex-Picture_x0020_9\" src=\"https://d33v4339jhl8k0.cloudfront.net/inline/87172/4bea86d77034e1c59ecfb2bb9bd5234871e774f1/ea4417351269cbe4e1ba5dabe135e55b66824532/image002.png\"/></a> <a href=\"https://www.facebook.com/AxiomWorkplaces/\"><img border=\"0\" width=\"30\" height=\"30\" style=\"width:0.3125in;height:0.3125in;\" alt=\"social-_0005_Vector-Smart-Object\" name=\"ex-Picture_x0020_10\" src=\"https://d33v4339jhl8k0.cloudfront.net/inline/87172/0deda5c7ed3cece7d7f1ac2bfaad308634e36200/3bb5ea8e79292980a5d2d99c5e589900d39d9d81/image003.png\"/></a> <a href=\"https://www.pinterest.com/axiomworkplaces\"><img border=\"0\" width=\"30\" height=\"30\" style=\"width:0.3125in;height:0.3125in;\" alt=\"social-_0004_Vector-Smart-Object\" name=\"ex-Picture_x0020_11\" src=\"https://d33v4339jhl8k0.cloudfront.net/inline/87172/a9953191fd63b1ee5733cff47616cc888252767e/b22b15965b844c33d29138a8e640c62f759c16f7/image004.png\"/></a><br><br><a href=\"https://axiomworkplaces.com.au/our-insight/what-does-the-future-of-work-look-like-for-employees-employers-and-workplaces/\"><img border=\"0\" width=\"623\" height=\"162\" style=\"width:6.4895in;height:1.6875in;\" name=\"ex-Picture_x0020_12\" src=\"https://d33v4339jhl8k0.cloudfront.net/inline/87172/1fe1dbb17333bd66976a3e70724b9ca07e58e6b0/a308d2462b2e486c14a4ab0faa692882080f11f3/image005.jpg\" alt=\"image005.jpg@01D6FA2B.E08468C0\"/></a><br><br>This e-mail may contain confidential and/or privileged information. If you are not the intended recipient (or have received this e-mail in error) please notify the sender immediately and destroy this e-mail. Any unauthorised copying, disclosure or distribution of the material in this e-mail is strictly forbidden. Axiom respects your privacy and is bound by the Australian Privacy Principles. If this email consists of direct marketing material and you would prefer to be removed from the mailing list, please reply to this email with the word \"Unsubscribe\" as the Subject.",
            "source": {
                "type": "email",
                "via": "customer"
            },
            "customer": {
                "id": 234333118,
                "first": "Sarah-Jane",
                "last": "Lamont",
                "photoUrl": "https://d33v4339jhl8k0.cloudfront.net/customer-avatar/05.png",
                "email": "sarah-jane.lamont@axiomworkplaces.com.au"
            },
            "createdBy": {
                "id": 234333118,
                "type": "customer",
                "first": "Sarah-Jane",
                "last": "Lamont",
                "photoUrl": "https://d33v4339jhl8k0.cloudfront.net/customer-avatar/05.png",
                "email": "sarah-jane.lamont@axiomworkplaces.com.au"
            },
            "assignedTo": {
                "id": 481974,
                "type": "user",
                "first": "Rica",
                "last": "Rosario Valencia",
                "photoUrl": "https://d33v4339jhl8k0.cloudfront.net/users/481974.341283.jpg",
                "email": "rica@wolfiq.com.au"
            },
            "savedReplyId": 0,
            "to": [],
            "cc": [],
            "bcc": [],
            "createdAt": "2021-02-03T01:55:57Z",
            "_embedded": {
                "attachments": [
                    {
                        "id": 332781114,
                        "filename": "image006.jpg",
                        "mimeType": "image/jpeg",
                        "width": 150,
                        "height": 68,
                        "size": 460,
                        "state": "valid",
                        "_links": {
                            "self": {
                                "href": "https://api.helpscout.net/v2/conversations/1414459698/attachments/332781114"
                            },
                            "data": {
                                "href": "https://api.helpscout.net/v2/conversations/1414459698/attachments/332781114/data"
                            },
                            "web": {
                                "href": "https://secure.helpscout.net/file/api/332781114/fe52b1697f8235dd2793bfd976fa738ffe3d5982/image006.jpg"
                            }
                        }
                    },
                    {
                        "id": 332781115,
                        "filename": "image007.jpg",
                        "mimeType": "image/jpeg",
                        "width": 30,
                        "height": 30,
                        "size": 344,
                        "state": "valid",
                        "_links": {
                            "self": {
                                "href": "https://api.helpscout.net/v2/conversations/1414459698/attachments/332781115"
                            },
                            "data": {
                                "href": "https://api.helpscout.net/v2/conversations/1414459698/attachments/332781115/data"
                            },
                            "web": {
                                "href": "https://secure.helpscout.net/file/api/332781115/490563c006dacfd48f26f791bc11409dbc02a459/image007.jpg"
                            }
                        }
                    },
                    {
                        "id": 332781116,
                        "filename": "image008.jpg",
                        "mimeType": "image/jpeg",
                        "width": 623,
                        "height": 162,
                        "size": 1560,
                        "state": "valid",
                        "_links": {
                            "self": {
                                "href": "https://api.helpscout.net/v2/conversations/1414459698/attachments/332781116"
                            },
                            "data": {
                                "href": "https://api.helpscout.net/v2/conversations/1414459698/attachments/332781116/data"
                            },
                            "web": {
                                "href": "https://secure.helpscout.net/file/api/332781116/f2c9d09f986372e9eef128209d2b610acb8404b3/image008.jpg"
                            }
                        }
                    }
                ]
            },
            "_links": {
                "assignedTo": {
                    "href": "https://api.helpscout.net/v2/users/481974"
                },
                "createdByCustomer": {
                    "href": "https://api.helpscout.net/v2/customers/234333118"
                },
                "customer": {
                    "href": "https://api.helpscout.net/v2/customers/234333118"
                }
            }
        },
        {
            "id": 4090504688,
            "type": "note",
            "status": "closed",
            "state": "published",
            "action": {
                "type": "default",
                "associatedEntities": {}
            },
            "body": "Logged 15 mins to Harvest",
            "source": {
                "type": "web",
                "via": "user"
            },
            "customer": {
                "id": 234333118,
                "first": "Sarah-Jane",
                "last": "Lamont",
                "photoUrl": "https://d33v4339jhl8k0.cloudfront.net/customer-avatar/05.png",
                "email": "sarah-jane.lamont@axiomworkplaces.com.au"
            },
            "createdBy": {
                "id": 481974,
                "type": "user",
                "first": "Rica",
                "last": "Rosario Valencia",
                "photoUrl": "https://d33v4339jhl8k0.cloudfront.net/users/481974.341283.jpg",
                "email": "rica@wolfiq.com.au"
            },
            "assignedTo": {
                "id": 481974,
                "type": "user",
                "first": "Rica",
                "last": "Rosario Valencia",
                "photoUrl": "https://d33v4339jhl8k0.cloudfront.net/users/481974.341283.jpg",
                "email": "rica@wolfiq.com.au"
            },
            "savedReplyId": 0,
            "to": [],
            "cc": [],
            "bcc": [],
            "createdAt": "2021-02-03T01:46:13Z",
            "_embedded": {
                "attachments": []
            },
            "_links": {
                "assignedTo": {
                    "href": "https://api.helpscout.net/v2/users/481974"
                },
                "createdByUser": {
                    "href": "https://api.helpscout.net/v2/users/481974"
                },
                "customer": {
                    "href": "https://api.helpscout.net/v2/customers/234333118"
                }
            }
        },
        {
            "id": 4090497232,
            "type": "message",
            "status": "active",
            "state": "published",
            "action": {
                "type": "original-author",
                "associatedEntities": {
                    "user": 481974
                }
            },
            "body": "Hi Sarah,<br /><br />Thank you for reaching out to us. Confirming that we have fixed the size of the images and they are ready for you to review.\u00a0<br /><br />Please let us know if you would like any further changes.",
            "source": {
                "type": "web",
                "via": "user"
            },
            "customer": {
                "id": 234333118,
                "first": "Sarah-Jane",
                "last": "Lamont",
                "photoUrl": "https://d33v4339jhl8k0.cloudfront.net/customer-avatar/05.png",
                "email": "sarah-jane.lamont@axiomworkplaces.com.au"
            },
            "createdBy": {
                "id": 481974,
                "type": "user",
                "first": "Rica",
                "last": "Rosario Valencia",
                "photoUrl": "https://d33v4339jhl8k0.cloudfront.net/users/481974.341283.jpg",
                "email": "rica@wolfiq.com.au"
            },
            "assignedTo": {
                "id": 481974,
                "type": "user",
                "first": "Rica",
                "last": "Rosario Valencia",
                "photoUrl": "https://d33v4339jhl8k0.cloudfront.net/users/481974.341283.jpg",
                "email": "rica@wolfiq.com.au"
            },
            "savedReplyId": 1621859,
            "to": [],
            "cc": [],
            "bcc": [],
            "createdAt": "2021-02-03T01:45:29Z",
            "_embedded": {
                "attachments": []
            },
            "_links": {
                "assignedTo": {
                    "href": "https://api.helpscout.net/v2/users/481974"
                },
                "createdByUser": {
                    "href": "https://api.helpscout.net/v2/users/481974"
                },
                "customer": {
                    "href": "https://api.helpscout.net/v2/customers/234333118"
                }
            }
        },
        {
            "id": 4090484421,
            "type": "note",
            "status": "pending",
            "state": "published",
            "action": {
                "type": "default",
                "associatedEntities": {}
            },
            "body": "<b class=\"mention-highlight\">@rica</b>\u00a0done updating images sizes, please check<br /><a href=\"https://axiomworkplaces.com.au/our-story/\">https://axiomworkplaces.com.au/our-story/</a><br /><br />time: 15mins<br />",
            "source": {
                "type": "web",
                "via": "user"
            },
            "customer": {
                "id": 234333118,
                "first": "Sarah-Jane",
                "last": "Lamont",
                "photoUrl": "https://d33v4339jhl8k0.cloudfront.net/customer-avatar/05.png",
                "email": "sarah-jane.lamont@axiomworkplaces.com.au"
            },
            "createdBy": {
                "id": 419638,
                "type": "user",
                "first": "Jaime",
                "last": "Velasquez",
                "photoUrl": "https://d33v4339jhl8k0.cloudfront.net/users/419638.341448.jpg",
                "email": "jaime@wolfiq.com.au"
            },
            "assignedTo": {
                "id": 481974,
                "type": "user",
                "first": "Rica",
                "last": "Rosario Valencia",
                "photoUrl": "https://d33v4339jhl8k0.cloudfront.net/users/481974.341283.jpg",
                "email": "rica@wolfiq.com.au"
            },
            "savedReplyId": 0,
            "to": [],
            "cc": [],
            "bcc": [],
            "createdAt": "2021-02-03T01:32:33Z",
            "_embedded": {
                "attachments": []
            },
            "_links": {
                "assignedTo": {
                    "href": "https://api.helpscout.net/v2/users/481974"
                },
                "createdByUser": {
                    "href": "https://api.helpscout.net/v2/users/419638"
                },
                "customer": {
                    "href": "https://api.helpscout.net/v2/customers/234333118"
                }
            }
        },
        {
            "id": 4090408825,
            "type": "note",
            "status": "active",
            "state": "published",
            "action": {
                "type": "default",
                "associatedEntities": {}
            },
            "body": "<b class=\"mention-highlight\">@jaime</b>\u00a0can you please take a look at the size of the images on this page under Our Team section:\u00a0https://axiomworkplaces.com.au/our-story/",
            "source": {
                "type": "web",
                "via": "user"
            },
            "customer": {
                "id": 234333118,
                "first": "Sarah-Jane",
                "last": "Lamont",
                "photoUrl": "https://d33v4339jhl8k0.cloudfront.net/customer-avatar/05.png",
                "email": "sarah-jane.lamont@axiomworkplaces.com.au"
            },
            "createdBy": {
                "id": 481974,
                "type": "user",
                "first": "Rica",
                "last": "Rosario Valencia",
                "photoUrl": "https://d33v4339jhl8k0.cloudfront.net/users/481974.341283.jpg",
                "email": "rica@wolfiq.com.au"
            },
            "assignedTo": {
                "id": 419638,
                "type": "user",
                "first": "Jaime",
                "last": "Velasquez",
                "photoUrl": "https://d33v4339jhl8k0.cloudfront.net/users/419638.341448.jpg",
                "email": "jaime@wolfiq.com.au"
            },
            "savedReplyId": 0,
            "to": [],
            "cc": [],
            "bcc": [],
            "createdAt": "2021-02-03T00:46:51Z",
            "_embedded": {
                "attachments": []
            },
            "_links": {
                "assignedTo": {
                    "href": "https://api.helpscout.net/v2/users/419638"
                },
                "createdByUser": {
                    "href": "https://api.helpscout.net/v2/users/481974"
                },
                "customer": {
                    "href": "https://api.helpscout.net/v2/customers/234333118"
                }
            }
        },
        {
            "id": 4090395516,
            "type": "customer",
            "status": "active",
            "state": "published",
            "action": {
                "type": "default",
                "associatedEntities": {}
            },
            "body": "<div class=\"ex-ex-\">\n<span style=\"font-size:10pt;font-family:Arial, sans-serif;\">Hi Heath,</span><br><span style=\"font-size:10pt;font-family:Arial, sans-serif;\"></span><p></p><br><span style=\"font-size:10pt;font-family:Arial, sans-serif;\">Could you please take a look at the team page of our website? I have added/updated some photos and it has skewed the frame of the team member: <a href=\"https://axiomworkplaces.com.au/our-story/\">https://axiomworkplaces.com.au/our-story/</a></span><br><span style=\"font-size:10pt;font-family:Arial, sans-serif;\"></span><p></p><br><span style=\"font-size:10pt;font-family:Arial, sans-serif;\">I have followed previous instructions which is to resize the profile image to 400x400 and save no larger than 200kb so I'm not sure what has gone wrong. It has been a while since I have added anyone.</span><br><span style=\"font-size:10pt;font-family:Arial, sans-serif;\"></span><p></p><br><span lang=\"en-us\" style=\"font-size:10pt;font-family:Arial, sans-serif;color:#000;\" xml:lang=\"en-us\">Kindest Regards,</span><br><span lang=\"en-us\" style=\"font-size:10pt;font-family:Verdana, sans-serif;color:#4A452A;\" xml:lang=\"en-us\"></span><p></p><br><div style=\"font-weight:bold;\"><span lang=\"en-us\" style=\"font-size:10pt;font-family:Arial, sans-serif;color:#000;\" xml:lang=\"en-us\">Sarah-Jane Lamont</span></div>\n<span lang=\"en-us\" style=\"font-size:10pt;font-family:Arial, sans-serif;color:#000;\" xml:lang=\"en-us\">Client Relations Executive Assistant</span><br><span lang=\"en-us\" style=\"font-size:10pt;font-family:Arial, sans-serif;color:#000;\" xml:lang=\"en-us\"></span><p></p><br><p class=\"ex-ex-\" style=\"margin-bottom:2pt;\"><b><span lang=\"en-us\" style=\"font-size:10pt;font-family:Arial, sans-serif;color:#000;\" xml:lang=\"en-us\">T </span></b> <span lang=\"en-us\" style=\"font-size:10pt;font-family:Arial, sans-serif;color:#000;\" xml:lang=\"en-us\">1300 11 22 32</span></p>\n<p class=\"ex-ex-\" style=\"margin-bottom:2pt;\"><b><span lang=\"en-us\" style=\"font-size:10pt;font-family:Arial, sans-serif;color:#000;\" xml:lang=\"en-us\">M </span></b> <span lang=\"en-us\" style=\"font-size:10pt;font-family:Arial, sans-serif;color:#000;\" xml:lang=\"en-us\">0421 478 501</span></p>\n<p class=\"ex-ex-\" style=\"margin-bottom:2pt;\"><b><span lang=\"en-us\" style=\"font-size:10pt;font-family:Arial, sans-serif;color:#000;\" xml:lang=\"en-us\">E </span></b> <span style=\"font-family:Arial, sans-serif;font-size:10pt;text-decoration:underline;\" lang=\"en-us\" xml:lang=\"en-us\"><a href=\"mailto:sarah-jane.lamont@axiomworkplaces.com.au\"><span>sarah-jane.lamont@axiomworkplaces.com.au</span></a><span style=\"color:#0563C1;\"></span></span></p>\n<p class=\"ex-ex-\" style=\"margin-bottom:2pt;\"><b><span lang=\"en-us\" style=\"font-size:10pt;font-family:Arial, sans-serif;\" xml:lang=\"en-us\">LI</span></b> <span style=\"font-size:10pt;font-family:Arial, sans-serif;\"><a href=\"https://www.linkedin.com/in/sarah-jane-lamont-93542627/\"><span>linkedin.com/in/sarah-jane-lamont-93542627/</span></a></span><b><span lang=\"en-us\" style=\"font-size:10pt;font-family:Arial, sans-serif;\" xml:lang=\"en-us\"></span></b></p>\n<p class=\"ex-ex-\" style=\"margin-bottom:2pt;\"><b><span lang=\"en-us\" style=\"font-size:10pt;font-family:Arial, sans-serif;\" xml:lang=\"en-us\">W</span></b> <span lang=\"en-us\" style=\"font-family:Arial, sans-serif;\" xml:lang=\"en-us\"><a href=\"http://axiomworkplaces.com.au/\"><span style=\"font-size:10pt;\">axiomworkplaces.com.au</span></a></span><span lang=\"en-us\" style=\"font-family:Arial, sans-serif;color:#32388E;\" xml:lang=\"en-us\"></span></p>\n<b><span lang=\"en-us\" style=\"font-size:10pt;color:#DB3745;\" xml:lang=\"en-us\"> </span></b><span lang=\"en-us\" xml:lang=\"en-us\"></span><br><a href=\"https://www.linkedin.com/company/axiom-workplaces\"><span lang=\"en-us\" style=\"text-decoration:none;\" xml:lang=\"en-us\"><img border=\"0\" width=\"30\" height=\"30\" style=\"width:0.3125in;height:0.3125in;\" id=\"ex-Picture_x0020_1\" src=\"https://d33v4339jhl8k0.cloudfront.net/inline/87172/d644de97f31914f7a7e6381db9f733c661441761/dd6bf8c51b8476941db76dc5de2f4720d835825e/image001.png\" alt=\"social-_0007_Vector-Smart-Object\" /></span></a><span lang=\"en-us\" xml:lang=\"en-us\"> </span> <a href=\"https://www.instagram.com/axiom_workplaces/\"><span lang=\"en-us\" style=\"text-decoration:none;\" xml:lang=\"en-us\"><img border=\"0\" width=\"30\" height=\"30\" style=\"width:0.3125in;height:0.3125in;\" id=\"ex-Picture_x0020_2\" src=\"https://d33v4339jhl8k0.cloudfront.net/inline/87172/6c27cb588e877f4969833c73a0731fcb56813f33/ea4417351269cbe4e1ba5dabe135e55b66824532/image002.png\" alt=\"social-_0006_Vector-Smart-Object\" /></span></a><span lang=\"en-us\" xml:lang=\"en-us\">  </span><a href=\"https://www.facebook.com/AxiomWorkplaces/\"><span lang=\"en-us\" style=\"text-decoration:none;\" xml:lang=\"en-us\"><img border=\"0\" width=\"30\" height=\"30\" style=\"width:0.3125in;height:0.3125in;\" id=\"ex-Picture_x0020_3\" src=\"https://d33v4339jhl8k0.cloudfront.net/inline/87172/94beb08cc3bbbfa38904bdd83acb6534be2fd11b/3bb5ea8e79292980a5d2d99c5e589900d39d9d81/image003.png\" alt=\"social-_0005_Vector-Smart-Object\" /></span></a><span lang=\"en-us\" xml:lang=\"en-us\">  </span><a href=\"https://www.pinterest.com/axiomworkplaces\"><span lang=\"en-us\" style=\"text-decoration:none;\" xml:lang=\"en-us\"><img border=\"0\" width=\"30\" height=\"30\" style=\"width:0.3125in;height:0.3125in;\" id=\"ex-Picture_x0020_4\" src=\"https://d33v4339jhl8k0.cloudfront.net/inline/87172/ae2a2d265ca9f75130116f0515ca59ca9c95a8b8/b22b15965b844c33d29138a8e640c62f759c16f7/image004.png\" alt=\"social-_0004_Vector-Smart-Object\" /></span></a><span lang=\"en-us\" xml:lang=\"en-us\"></span><br><span lang=\"en-us\" xml:lang=\"en-us\"> </span><br><a href=\"https://axiomworkplaces.com.au/our-insight/what-does-the-future-of-work-look-like-for-employees-employers-and-workplaces/\"><span lang=\"en-us\" style=\"text-decoration:none;\" xml:lang=\"en-us\"><img border=\"0\" width=\"623\" height=\"162\" style=\"width:6.4895in;height:1.6875in;\" id=\"ex-Picture_x0020_5\" src=\"https://d33v4339jhl8k0.cloudfront.net/inline/87172/d69d183f7609a48bd053d6ed9c04bcb55d6c7497/a308d2462b2e486c14a4ab0faa692882080f11f3/image007.jpg\" alt=\"https://d33v4339jhl8k0.cloudfront.net/inline/87172/d69d183f7609a48bd053d6ed9c04bcb55d6c7497/a308d2462b2e486c14a4ab0faa692882080f11f3/image007.jpg\" /></span></a><span lang=\"en-us\" xml:lang=\"en-us\"></span><br><p class=\"ex-ex-\" style=\"margin-top:14pt;line-height:13.2pt;\"><span lang=\"en-gb\" style=\"font-size:8pt;font-family:Arial, sans-serif;\" xml:lang=\"en-gb\">This e-mail may contain confidential and/or privileged information. If you are not the intended recipient (or have received this e-mail in error) please notify the sender immediately and destroy this e-mail. Any unauthorised copying, disclosure or distribution of the material in this e-mail is strictly forbidden. Axiom respects your privacy and is bound by the Australian Privacy Principles. If this email consists of direct marketing material and you would prefer to be removed from the mailing list, please reply to this email with the word \"Unsubscribe\" as the Subject.</span><span lang=\"en-us\" style=\"font-size:8pt;font-family:Arial, sans-serif;\" xml:lang=\"en-us\"></span></p>\n<br></div>",
            "source": {
                "type": "email",
                "via": "customer"
            },
            "customer": {
                "id": 234333118,
                "first": "Sarah-Jane",
                "last": "Lamont",
                "photoUrl": "https://d33v4339jhl8k0.cloudfront.net/customer-avatar/05.png",
                "email": "sarah-jane.lamont@axiomworkplaces.com.au"
            },
            "createdBy": {
                "id": 234333118,
                "type": "customer",
                "first": "Sarah-Jane",
                "last": "Lamont",
                "photoUrl": "https://d33v4339jhl8k0.cloudfront.net/customer-avatar/05.png",
                "email": "sarah-jane.lamont@axiomworkplaces.com.au"
            },
            "assignedTo": {
                "id": 1,
                "first": "Help",
                "last": "Scout",
                "email": "none@nowhere.com"
            },
            "savedReplyId": 0,
            "to": [],
            "cc": [],
            "bcc": [],
            "createdAt": "2021-02-03T00:39:12Z",
            "_embedded": {
                "attachments": []
            },
            "_links": {
                "assignedTo": {
                    "href": "https://api.helpscout.net/v2/users/1"
                },
                "createdByCustomer": {
                    "href": "https://api.helpscout.net/v2/customers/234333118"
                },
                "customer": {
                    "href": "https://api.helpscout.net/v2/customers/234333118"
                }
            }
        }
    ]
}